freem_bots/__init__.py
freem_bots/asyncio_queue_log_handler.py
freem_bots/configuration.py
freem_bots/demoji_wrp.py
freem_bots/discord_bot.py
freem_bots/py.typed
freem_bots/random_provider.py
freem_bots/tts.py
freem_bots-0.26.0.dist-info/METADATA
freem_bots-0.26.0.dist-info/WHEEL
freem_bots-0.26.0.dist-info/licenses/LICENSE
freem_bots-0.26.0.dist-info/RECORD
