Metadata-Version: 2.4
Name: freem-bots
Version: 0.26.0
Summary: Abstractions over Discord with simple TTS voice support
License: MIT
License-File: LICENSE
Author: Freem
Author-email: freemanovec@protonmail.com
Requires-Python: >=3.12,<3.13
Classifier: License :: OSI Approved :: MIT License
Classifier: Programming Language :: Python :: 3
Classifier: Programming Language :: Python :: 3.12
Requires-Dist: aiohttp (>=3.12.15,<4.0.0)
Requires-Dist: async-timeout (>=5.0.1,<6.0.0)
Requires-Dist: demoji (>=1.1.0,<2.0.0)
Requires-Dist: miniaudio (>=1.61,<2.0)
Requires-Dist: numpy (>=2.3.2,<3.0.0)
Requires-Dist: pedalboard (>=0.9.17,<0.10.0)
Requires-Dist: py-cord[voice] (>=2,<3)
Requires-Dist: pynacl (>=1.5.0,<2.0.0)
Requires-Dist: requests (>=2.32.5,<3.0.0)
Requires-Dist: soundfile (>=0.13.1,<0.14.0)
